docs/api.md
docs/conf.yaml
docs/examples.md
docs/index.md
docs/usage.md
docsmaker/__init__.py
docsmaker/__main__.py
docsmaker/builder.py
docsmaker/cli.py
docsmaker/config.py
docsmaker/parser.py
docsmaker/utils.py
docsmakerpy-1.3.0.dist-info/licenses/LICENSE
tests/__init__.py
tests/conftest.py
tests/test_builder.py
tests/test_cli.py
tests/test_config.py
tests/test_integration.py
tests/test_parser.py
themes/default/config.yaml
themes/default/assets/css/style.css
themes/default/assets/js/script.js
themes/default/templates/base.html
themes/default/templates/sidebar.html
docsmakerpy-1.3.0.dist-info/METADATA
docsmakerpy-1.3.0.dist-info/WHEEL
docsmakerpy-1.3.0.dist-info/entry_points.txt
docsmakerpy-1.3.0.dist-info/top_level.txt
docsmakerpy-1.3.0.dist-info/RECORD
