Metadata-Version: 2.4
Name: docsmakerpy
Version: 1.3.0
Summary: Generate static documentation sites from Markdown files with theming and plugins.
Author: Othmane BLIAL
License: MIT
Project-URL: Repository, https://github.com/OthmaneBlial/docsmaker
Project-URL: Homepage, https://github.com/OthmaneBlial/docsmaker
Classifier: Development Status :: 3 - Alpha
Classifier: Intended Audience :: Developers
Classifier: License :: OSI Approved :: MIT License
Classifier: Programming Language :: Python :: 3
Classifier: Programming Language :: Python :: 3.8
Classifier: Programming Language :: Python :: 3.9
Classifier: Programming Language :: Python :: 3.10
Classifier: Programming Language :: Python :: 3.11
Classifier: Programming Language :: Python :: 3.12
Classifier: Topic :: Documentation
Classifier: Topic :: Software Development :: Documentation
Requires-Python: >=3.8
License-File: LICENSE
Requires-Dist: typer>=0.9.0
Requires-Dist: pyyaml>=6.0
Requires-Dist: pydantic>=2.0
Requires-Dist: markdown-it-py>=3.0
Requires-Dist: mdit-py-plugins>=0.4.0
Requires-Dist: jinja2>=3.0
Provides-Extra: serve
Requires-Dist: livereload>=2.6; extra == "serve"
Provides-Extra: dev
Requires-Dist: pytest>=7.0; extra == "dev"
Requires-Dist: pytest-cov>=4.0; extra == "dev"
Requires-Dist: pytest-mock>=3.0; extra == "dev"
Requires-Dist: tox>=4.0; extra == "dev"
Dynamic: license-file
